resizeimage/__init__.py
resizeimage/helpers.py
resizeimage/imageexceptions.py
resizeimage/resizeimage.py
tests/__init__.py
tests/tests.py
python_resize_image-1.1.20.dist-info/LICENSE
python_resize_image-1.1.20.dist-info/METADATA
python_resize_image-1.1.20.dist-info/WHEEL
python_resize_image-1.1.20.dist-info/top_level.txt
python_resize_image-1.1.20.dist-info/RECORD
