Metadata-Version: 1.1
Name: python-resize-image
Version: 1.1.20
Summary: A Small python package to easily resize images
Home-page: https://github.com/VingtCinq/python-resize-image
Author: Charles TISSIER
Author-email: charles@vingtcinq.io
License: MIT
Keywords: image resize resizing python
Platform: UNKNOWN
Classifier: Development Status :: 5 - Production/Stable
Classifier: Intended Audience :: Developers
Classifier: Topic :: Software Development :: Libraries :: Python Modules
Classifier: License :: OSI Approved :: MIT License
Classifier: Programming Language :: Python :: 2.7
Classifier: Programming Language :: Python :: 3
Classifier: Programming Language :: Python :: 3.4
Classifier: Programming Language :: Python :: 3.5
Classifier: Programming Language :: Python :: 3.6
